pytrackdat/__init__.py
pytrackdat/analysis.py
pytrackdat/common-passwords.txt.gz
pytrackdat/common.py
pytrackdat/generation.py
pytrackdat/app_includes/export_csv.py
pytrackdat/app_includes/export_labels.py
pytrackdat/app_includes/import_csv.py
pytrackdat/app_includes/templates/admin/core/change_list.html
pytrackdat/app_includes/templates/admin/core/csv_form.html
pytrackdat/os_scripts/create_django_site.bash
pytrackdat/os_scripts/create_django_site.bat
pytrackdat/os_scripts/run_site_setup.bash
pytrackdat/os_scripts/run_site_setup.bat
pytrackdat/util_files/Dockerfile.template
pytrackdat/util_files/docker-compose.yml
pytrackdat/util_files/export_labels.R
pytrackdat/util_files/install_dependencies.R
pytrackdat/util_files/nginx.conf
pytrackdat/util_files/requirements.txt
pytrackdat/util_files/requirements_setup.txt
tmp/__init__.py
pytrackdat-0.2.1.dist-info/LICENSE
pytrackdat-0.2.1.dist-info/METADATA
pytrackdat-0.2.1.dist-info/WHEEL
pytrackdat-0.2.1.dist-info/entry_points.txt
pytrackdat-0.2.1.dist-info/top_level.txt
pytrackdat-0.2.1.dist-info/RECORD
