Metadata-Version: 2.1
Name: pytrackdat
Version: 0.2.1
Summary: A utility for assisting in the creation of online databases for biological data.
Home-page: https://github.com/ColauttiLab/PyTrackDat
Author: David Lougheed
Author-email: david.lougheed@gmail.com
License: GPLv3
Platform: UNKNOWN
Classifier: Programming Language :: Python :: 3 :: Only
Classifier: License :: OSI Approved :: GNU General Public License v3 (GPLv3)
Classifier: Operating System :: OS Independent
Requires-Python: ~=3.6
Requires-Dist: wheel
Requires-Dist: virtualenv
